apkupload/__init__.py
apkupload/__main__.py
apkupload/upload.py
apkupload-0.0.21.dist-info/LICENSE
apkupload-0.0.21.dist-info/METADATA
apkupload-0.0.21.dist-info/WHEEL
apkupload-0.0.21.dist-info/entry_points.txt
apkupload-0.0.21.dist-info/top_level.txt
apkupload-0.0.21.dist-info/RECORD
