Metadata-Version: 2.1
Name: apkupload
Version: 0.0.21
Summary: apk 上传
Home-page: https://malinkang.com
Author: malinkang
Author-email: linkang.ma@gmail.com
Classifier: Programming Language :: Python :: 3
Classifier: License :: OSI Approved :: MIT License
Classifier: Operating System :: OS Independent
License-File: LICENSE
